{
    "key": "group_5fa170e2a294f",
    "title": "Signposting options",
    "fields": [
        {
            "key": "field_5fa170f3be560",
            "label": "Action link text",
            "name": "action_link_text",
            "type": "text",
            "instructions": "Action text that appears in signposting cards and similar - defaults to Read more...",
            "required": 0,
            "conditional_logic": 0,
            "wrapper": {
                "width": "",
                "class": "",
                "id": ""
            },
            "default_value": "Read more",
            "placeholder": "",
            "prepend": "",
            "append": "",
            "maxlength": ""
        }
    ],
    "location": [
        [
            {
                "param": "post_type",
                "operator": "==",
                "value": "post"
            }
        ],
        [
            {
                "param": "post_type",
                "operator": "==",
                "value": "page"
            }
        ],
        [
            {
                "param": "post_type",
                "operator": "==",
                "value": "project"
            }
        ],
        [
            {
                "param": "post_type",
                "operator": "==",
                "value": "latest-update"
            }
        ]
    ],
    "menu_order": 0,
    "position": "side",
    "style": "default",
    "label_placement": "top",
    "instruction_placement": "label",
    "hide_on_screen": "",
    "active": true,
    "description": "",
    "modified": 1617017289
}